pysubtools/__init__.py
pysubtools/formats.py
pysubtools/sublib.py
pysubtools-0.1.dist-info/METADATA
pysubtools-0.1.dist-info/WHEEL
pysubtools-0.1.dist-info/top_level.txt
pysubtools-0.1.dist-info/RECORD
